mem1/__init__.py
mem1/config.py
mem1/langchain_middleware.py
mem1/llm.py
mem1/memory.py
mem1/memory_md.py
mem1/memory_tools.py
mem1/prompts.py
mem1/storage.py
mem1-0.1.1.dist-info/METADATA
mem1-0.1.1.dist-info/WHEEL
mem1-0.1.1.dist-info/RECORD
