Metadata-Version: 2.4
Name: mem1
Version: 0.1.1
Summary: 基于云服务的用户记忆系统
Project-URL: Homepage, https://github.com/sougannkyou/mem1
Project-URL: Repository, https://github.com/sougannkyou/mem1
Author: Song
License: MIT
Keywords: langchain,llm,memory,user-profile
Classifier: Development Status :: 3 - Alpha
Classifier: Intended Audience :: Developers
Classifier: License :: OSI Approved :: MIT License
Classifier: Programming Language :: Python :: 3
Classifier: Programming Language :: Python :: 3.12
Classifier: Programming Language :: Python :: 3.13
Requires-Python: >=3.12
Requires-Dist: dashscope>=1.14.0
Requires-Dist: elasticsearch>=8.0.0
Requires-Dist: openai>=1.0.0
Requires-Dist: pydantic>=2.0.0
Requires-Dist: python-dotenv>=1.0.0
Provides-Extra: dev
Requires-Dist: ipython>=8.0.0; extra == 'dev'
